zooper_premium_handbags_dataset/premiumhandbags8.py
zooper_premium_handbags_dataset-0.1.4.dist-info/LICENSE
zooper_premium_handbags_dataset-0.1.4.dist-info/METADATA
zooper_premium_handbags_dataset-0.1.4.dist-info/WHEEL
zooper_premium_handbags_dataset-0.1.4.dist-info/top_level.txt
zooper_premium_handbags_dataset-0.1.4.dist-info/RECORD
